{
	"draft": false,
	"emoji": "🧫",
	"question": {
		"short": "Do GMOs impact human health?",
		"long": "Do GMOs have an impact on consumer health?"
	},
	"description": "Results from studies evaluating the effect of food products containing GMOs on human health.",
	"tags": [
		"food",
		"GMO",
		"health",
		"agriculture"
	],
	"consensus": {
		"no_consensus": {
			"emoji": "🤷",
			"text": "No consensus yet",
			"description": "The literature has not yet reached a consensus on the effects of GMOs on human health",
			"color": "Gray",
			"coherence": {
				"no": 0.5,
				"yes_but_low_confidence": 0.5,
				"yes_but_small_effect": 0.5,
				"yes": 0.5
			}
		},
		"no": {
			"emoji": "👎",
			"text": "No",
			"description": "The literature suggests that GMOs have no effects on human health",
			"color": "Red",
			"coherence": {
				"no": 1,
				"yes_but_low_confidence": 0,
				"yes_but_small_effect": 0,
				"yes_unlike_literature": 0
			}
		},
		"towards_no": {
			"emoji": "⬅️",
			"text": "Towards no",
			"description": "The literature suggests that GMOs probably have no effects on human health, but more research is needed",
			"color": "Red1H",
			"coherence": {
				"no": 0.75,
				"yes_but_low_confidence": 0.25,
				"yes_but_small_effect": 0.25,
				"yes_unlike_literature": 0.25
			}
		},
		"towards_yes": {
			"emoji": "➡️",
			"text": "Towards yes",
			"description": "The literature suggests that GMOs may have an impact on human health, but more research is needed",
			"color": "Green1H",
			"coherence": {
				"no_unlike_literature": 0.25,
				"yes_but_low_confidence": 0.75,
				"yes_but_small_effect": 0.75,
				"yes": 0.75
			}
		},
		"yes": {
			"emoji": "👍",
			"text": "Yes",
			"description": "The literature suggests that GMOs have an impact on human health",
			"color": "Green",
			"coherence": {
				"no_unlike_literature": 0,
				"yes_but_low_confidence": 1,
				"yes_but_small_effect": 1,
				"yes": 1
			}
		}
	},
	"conclusion_groups": {
		"no": {
			"text": "No",
			"color": "Red"
		},
		"no_but": {
			"text": "No but...",
			"color": "Red1H"
		},
		"more_research_needed": {
			"text": "More research needed",
			"color": "Gray"
		},
		"yes_but": {
			"text": "Yes but...",
			"color": "Green1H"
		},
		"yes": {
			"text": "Yes",
			"color": "Green"
		}
	},
	"conclusions": {
		"no": {
			"group": "no",
			"emoji": "👎",
			"text": "No",
			"description": "The results of the paper show no significant impact on human health of the GMOs evaluated",
			"p_value": false
		},
		"no_unlike_literature": {
			"group": "no_but",
			"emoji": "↩️",
			"text": "No unlike literature",
			"description": "The results of the paper show no significant impact on human health of the GMOs evaluated, unlike what is reported in the literature",
			"p_value": false
		},
		"yes_but_low_confidence": {
			"group": "yes_but",
			"emoji": "🤔",
			"text": "Yes but low confidence",
			"description": "The results of the paper suggest that the GMOs evaluated may have an impact on human health, but the evidence is not strong",
			"p_value": true
		},
		"yes_but_small_effect": {
			"group": "yes_but",
			"emoji": "🤏",
			"text": "Yes but small effect",
			"description": "The results of the paper suggest that the GMOs evaluated may have a small impact on human health",
			"p_value": true
		},
		"yes_unlike_literature": {
			"group": "yes_but",
			"emoji": "↪️",
			"text": "Yes unlike literature",
			"description": "The results of the paper suggest that the GMOs evaluated have an impact on human health, unlike what is reported in the literature",
			"p_value": true
		},
		"yes": {
			"group": "yes",
			"emoji": "👍",
			"text": "Yes",
			"description": "The results of the paper suggest that the GMOs evaluated have an impact on human health",
			"p_value": true
		}
	},
	"type": {
		"no_causality": false,
		"no_random": false,
		"no_blind": false,
		"any": false
	},
	"on": {
		"any_animal": false,
		"any": false
	},
	"no_sample_size": false,
	"papers": [
		{
			"id": "W2010228015",
			"title": "test",
			"authors": [
				"David A. Wolfe",
				"Tracy Macpherson",
				"Ronald Blount",
				"Vicky V. Wolfe"
			],
			"year": 1986,
			"link": "https://doi.org/10.1016/0145-2134(86)90036-0",
			"journal": {
				"status": "Found",
				"id": "S53055215",
				"retracted": false
			},
			"citations": {
				"count": 68,
				"critics": false
			},
			"results": {
				"consensus": "yes",
				"conclusion": "yes",
				"indirect": false
			},
			"quote": "Relative to controls, children who received the program showed an overall increase in knowledge of correct actions to take in the event of potential or actual abuse.",
			"type": "RandomizedControlledTrial",
			"on": "Humans",
			"sample_size": 290,
			"p_value": {
				"value": 0.001,
				"less_than": true
			},
			"conflict_of_interest": false,
			"notes": []
		}
	]
}
